opendatahub/__init__.py
opendatahub/__main__.py
opendatahub/__version__.py
opendatahub/exception.py
opendatahub/utils.py
opendatahub-0.0.1b0.dist-info/LICENSE
opendatahub-0.0.1b0.dist-info/METADATA
opendatahub-0.0.1b0.dist-info/WHEEL
opendatahub-0.0.1b0.dist-info/entry_points.txt
opendatahub-0.0.1b0.dist-info/top_level.txt
opendatahub-0.0.1b0.dist-info/RECORD
