Metadata-Version: 2.1
Name: opendatahub
Version: 0.0.1b0
Summary: Python SDK for explore opendatahub datasets.
Home-page: https://gitlab.shlab.tech/dps/opendatalab-python-sdk/-/tree/dev-datahub
Author: Wang Rui
Author-email: wangrui@pjlab.org.cn
License: MIT
Project-URL: Bug Tracker, https://gitlab.shlab.tech/dps/opendatalab-python-sdk/-/tree/dev-datahub/-/issues
Keywords: opendatahub,dataset
Platform: UNKNOWN
Classifier: Programming Language :: Python :: 3
Classifier: License :: OSI Approved :: MIT License
Classifier: Operating System :: OS Independent
Requires-Python: >=3.6
License-File: LICENSE
Requires-Dist: requests
Requires-Dist: oss2
Requires-Dist: Click
Requires-Dist: tqdm
